LICENSE
README.md
setup.py
io_connect/__init__.py
io_connect/constants.py
io_connect.egg-info/PKG-INFO
io_connect.egg-info/SOURCES.txt
io_connect.egg-info/dependency_links.txt
io_connect.egg-info/requires.txt
io_connect.egg-info/top_level.txt
io_connect/async_connectors/__init__.py
io_connect/async_connectors/alerts_handler.py
io_connect/async_connectors/bruce_handler.py
io_connect/async_connectors/data_access.py
io_connect/async_connectors/events_handler.py
io_connect/async_connectors/file_logger.py
io_connect/async_connectors/weather_handler.py
io_connect/connectors/__init__.py
io_connect/connectors/alerts_handler.py
io_connect/connectors/bruce_handler.py
io_connect/connectors/data_access.py
io_connect/connectors/events_handler.py
io_connect/connectors/file_logger.py
io_connect/connectors/mqtt_handler.py
io_connect/connectors/weather_handler.py
io_connect/utilities/__init__.py
io_connect/utilities/schemas.py
io_connect/utilities/store.py