Metadata-Version: 2.1
Name: io-connect
Version: 1.6.6
Summary: io connect library
Author: Faclon-Labs
Author-email: datascience@faclon.com
Classifier: Programming Language :: Python :: 3.9
Classifier: Programming Language :: Python :: 3.10
Classifier: Programming Language :: Python :: 3.11
Classifier: Programming Language :: Python :: 3.12
Classifier: License :: OSI Approved :: MIT License
Classifier: Operating System :: OS Independent
Requires-Python: >=3.9
Provides-Extra: all
License-File: LICENSE
